Workbook

Sheet Lisez-moi
A1: Cahier de test — Léo et place de marché Finjaro
A2: Version | B2: 1.0 — 30/09/2026 — préparé pour l'équipe de test
A3: But | B3: Vérifier une par une les fonctionnalités de Léo (les agents IA) et de la place de marché Finjaro, noter ce qui marche et ce qui casse, avec assez de détails pour qu'on puisse corriger.
A4: Où tester | B4: Préproduction uniquement : https://staging-finjaro.finjaro.workers.dev — ne jamais tester sur finjaro.net (c'est la production : les applications Android et iOS la chargent directement).
A5: Comptes | B5: Utilisez uniquement les comptes de test fournis par Beau (marqués « test » dans la base, exclus de tous les chiffres). Aucun mot de passe n'est écrit dans ce fichier.
A6: Données | B6: Aucune donnée réelle : pas de vrai client, pas de vrai numéro, pas de vraie carte. Inventez des noms clairement fictifs (« Boutique Test », « Client Test »).
A8: Comment remplir
A9: Colonnes à remplir | B9: Seules les colonnes à en-tête doré (Statut → N° anomalie), fond jaune pâle, sont à remplir. Ne modifiez pas les colonnes terracotta (le scénario).
A10: Statut | B10: À tester (par défaut) · OK : le résultat attendu est obtenu · KO : ça ne marche pas → créer une anomalie · Bloqué : impossible de tester (prérequis manquant) · Non applicable.
A11: Résultat obtenu | B11: Ce que vous avez vraiment vu, en une ou deux phrases. Obligatoire si KO ou Bloqué.
A12: Remarques | B12: Tout ce qui gêne sans être une panne : lenteur, texte peu clair, faute, bouton mal placé, idée d'amélioration.
A13: Anomalies | B13: Chaque KO a une ligne dans la feuille « Anomalies » (le numéro ANO-xxx se crée tout seul dès que le titre est rempli). Reportez ce numéro dans la colonne « N° anomalie » du cas.
A14: Gravité | B14: Bloquante : on ne peut pas continuer (connexion, commande impossible) · Majeure : fonction cassée mais contournable · Mineure : gêne légère · Cosmétique : affichage, texte, alignement.
A15: Capture | B15: Une capture d'écran ou une courte vidéo par anomalie, en lien (Drive, WhatsApp…). Précisez l'appareil et le navigateur (ex. « Samsung A14, Chrome »).
A16: Deux formats | B16: Testez sur téléphone ET sur grand écran quand la colonne « Appareil » l'indique : un écran correct sur téléphone peut être cassé sur ordinateur, et inversement.
A17: Tableau de bord | B17: Se remplit tout seul : nombre de cas OK / KO / bloqués par module et anomalies ouvertes par gravité.
A19: Exemple de cas rempli
A20: Cas | B20: LEO-012 · Salons et messages · Écrire dans un salon
A21: Statut | B21: KO
A22: Résultat obtenu | B22: Le message part, mais aucun agent ne répond après 60 s. « Kwame écrit… » reste affiché.
A23: Remarques | B23: Même chose dans le salon Marketing. Ça marche après rechargement de la page.
A24: Testeur · Date | B24: Testeur A · 01/10/2026
A25: N° anomalie | B25: ANO-001
A27: Exemple d'anomalie
A28: Titre court | B28: Aucun agent ne répond dans le salon Direction
A29: Gravité · Statut | B29: Majeure · Ouverte
A30: Étapes | B30: 1. Se connecter avec le compte de test · 2. Ouvrir l'entreprise « Test Cabinet » · 3. Salon Direction · 4. Écrire « Bonjour, où en est-on ? »
A31: Attendu / obtenu | B31: Attendu : réponse d'un agent en quelques secondes · Obtenu : aucune réponse après 60 s
A32: Appareil | B32: Ordinateur Windows 11, Chrome 140

Sheet Tableau de bord
A1: Cahier de test — Léo et place de marché Finjaro
A2: Se met à jour tout seul à partir des colonnes « Statut » des feuilles Léo et Place de marché.
A4: Léo
A5: Module | B5: Cas | C5: OK | D5: KO | E5: Bloqué | F5: À tester | G5: Non applicable | H5: % passé
A6: Accès et compte | B6: =COUNTIF('Léo'!$B$2:$B$500,$A6) | C6: =COUNTIFS('Léo'!$B$2:$B$500,$A6,'Léo'!$K$2:$K$500,"OK") | D6: =COUNTIFS('Léo'!$B$2:$B$500,$A6,'Léo'!$K$2:$K$500,"KO") | E6: =COUNTIFS('Léo'!$B$2:$B$500,$A6,'Léo'!$K$2:$K$500,"Bloqué") | F6: =COUNTIFS('Léo'!$B$2:$B$500,$A6,'Léo'!$K$2:$K$500,"À tester") | G6: =COUNTIFS('Léo'!$B$2:$B$500,$A6,'Léo'!$K$2:$K$500,"Non applicable") | H6: =IF(B6-G6=0,0,C6/(B6-G6))
A7: Fonder une entreprise | B7: =COUNTIF('Léo'!$B$2:$B$500,$A7) | C7: =COUNTIFS('Léo'!$B$2:$B$500,$A7,'Léo'!$K$2:$K$500,"OK") | D7: =COUNTIFS('Léo'!$B$2:$B$500,$A7,'Léo'!$K$2:$K$500,"KO") | E7: =COUNTIFS('Léo'!$B$2:$B$500,$A7,'Léo'!$K$2:$K$500,"Bloqué") | F7: =COUNTIFS('Léo'!$B$2:$B$500,$A7,'Léo'!$K$2:$K$500,"À tester") | G7: =COUNTIFS('Léo'!$B$2:$B$500,$A7,'Léo'!$K$2:$K$500,"Non applicable") | H7: =IF(B7-G7=0,0,C7/(B7-G7))
A8: Salons et messages | B8: =COUNTIF('Léo'!$B$2:$B$500,$A8) | C8: =COUNTIFS('Léo'!$B$2:$B$500,$A8,'Léo'!$K$2:$K$500,"OK") | D8: =COUNTIFS('Léo'!$B$2:$B$500,$A8,'Léo'!$K$2:$K$500,"KO") | E8: =COUNTIFS('Léo'!$B$2:$B$500,$A8,'Léo'!$K$2:$K$500,"Bloqué") | F8: =COUNTIFS('Léo'!$B$2:$B$500,$A8,'Léo'!$K$2:$K$500,"À tester") | G8: =COUNTIFS('Léo'!$B$2:$B$500,$A8,'Léo'!$K$2:$K$500,"Non applicable") | H8: =IF(B8-G8=0,0,C8/(B8-G8))
A9: Agents | B9: =COUNTIF('Léo'!$B$2:$B$500,$A9) | C9: =COUNTIFS('Léo'!$B$2:$B$500,$A9,'Léo'!$K$2:$K$500,"OK") | D9: =COUNTIFS('Léo'!$B$2:$B$500,$A9,'Léo'!$K$2:$K$500,"KO") | E9: =COUNTIFS('Léo'!$B$2:$B$500,$A9,'Léo'!$K$2:$K$500,"Bloqué") | F9: =COUNTIFS('Léo'!$B$2:$B$500,$A9,'Léo'!$K$2:$K$500,"À tester") | G9: =COUNTIFS('Léo'!$B$2:$B$500,$A9,'Léo'!$K$2:$K$500,"Non applicable") | H9: =IF(B9-G9=0,0,C9/(B9-G9))
A10: Tâches et missions | B10: =COUNTIF('Léo'!$B$2:$B$500,$A10) | C10: =COUNTIFS('Léo'!$B$2:$B$500,$A10,'Léo'!$K$2:$K$500,"OK") | D10: =COUNTIFS('Léo'!$B$2:$B$500,$A10,'Léo'!$K$2:$K$500,"KO") | E10: =COUNTIFS('Léo'!$B$2:$B$500,$A10,'Léo'!$K$2:$K$500,"Bloqué") | F10: =COUNTIFS('Léo'!$B$2:$B$500,$A10,'Léo'!$K$2:$K$500,"À tester") | G10: =COUNTIFS('Léo'!$B$2:$B$500,$A10,'Léo'!$K$2:$K$500,"Non applicable") | H10: =IF(B10-G10=0,0,C10/(B10-G10))
A11: Réunions | B11: =COUNTIF('Léo'!$B$2:$B$500,$A11) | C11: =COUNTIFS('Léo'!$B$2:$B$500,$A11,'Léo'!$K$2:$K$500,"OK") | D11: =COUNTIFS('Léo'!$B$2:$B$500,$A11,'Léo'!$K$2:$K$500,"KO") | E11: =COUNTIFS('Léo'!$B$2:$B$500,$A11,'Léo'!$K$2:$K$500,"Bloqué") | F11: =COUNTIFS('Léo'!$B$2:$B$500,$A11,'Léo'!$K$2:$K$500,"À tester") | G11: =COUNTIFS('Léo'!$B$2:$B$500,$A11,'Léo'!$K$2:$K$500,"Non applicable") | H11: =IF(B11-G11=0,0,C11/(B11-G11))
A12: Voix et appels | B12: =COUNTIF('Léo'!$B$2:$B$500,$A12) | C12: =COUNTIFS('Léo'!$B$2:$B$500,$A12,'Léo'!$K$2:$K$500,"OK") | D12: =COUNTIFS('Léo'!$B$2:$B$500,$A12,'Léo'!$K$2:$K$500,"KO") | E12: =COUNTIFS('Léo'!$B$2:$B$500,$A12,'Léo'!$K$2:$K$500,"Bloqué") | F12: =COUNTIFS('Léo'!$B$2:$B$500,$A12,'Léo'!$K$2:$K$500,"À tester") | G12: =COUNTIFS('Léo'!$B$2:$B$500,$A12,'Léo'!$K$2:$K$500,"Non applicable") | H12: =IF(B12-G12=0,0,C12/(B12-G12))
A13: Rapports et tableau de bord | B13: =COUNTIF('Léo'!$B$2:$B$500,$A13) | C13: =COUNTIFS('Léo'!$B$2:$B$500,$A13,'Léo'!$K$2:$K$500,"OK") | D13: =COUNTIFS('Léo'!$B$2:$B$500,$A13,'Léo'!$K$2:$K$500,"KO") | E13: =COUNTIFS('Léo'!$B$2:$B$500,$A13,'Léo'!$K$2:$K$500,"Bloqué") | F13: =COUNTIFS('Léo'!$B$2:$B$500,$A13,'Léo'!$K$2:$K$500,"À tester") | G13: =COUNTIFS('Léo'!$B$2:$B$500,$A13,'Léo'!$K$2:$K$500,"Non applicable") | H13: =IF(B13-G13=0,0,C13/(B13-G13))
A14: Vues et outils | B14: =COUNTIF('Léo'!$B$2:$B$500,$A14) | C14: =COUNTIFS('Léo'!$B$2:$B$500,$A14,'Léo'!$K$2:$K$500,"OK") | D14: =COUNTIFS('Léo'!$B$2:$B$500,$A14,'Léo'!$K$2:$K$500,"KO") | E14: =COUNTIFS('Léo'!$B$2:$B$500,$A14,'Léo'!$K$2:$K$500,"Bloqué") | F14: =COUNTIFS('Léo'!$B$2:$B$500,$A14,'Léo'!$K$2:$K$500,"À tester") | G14: =COUNTIFS('Léo'!$B$2:$B$500,$A14,'Léo'!$K$2:$K$500,"Non applicable") | H14: =IF(B14-G14=0,0,C14/(B14-G14))
A15: Atelier de code | B15: =COUNTIF('Léo'!$B$2:$B$500,$A15) | C15: =COUNTIFS('Léo'!$B$2:$B$500,$A15,'Léo'!$K$2:$K$500,"OK") | D15: =COUNTIFS('Léo'!$B$2:$B$500,$A15,'Léo'!$K$2:$K$500,"KO") | E15: =COUNTIFS('Léo'!$B$2:$B$500,$A15,'Léo'!$K$2:$K$500,"Bloqué") | F15: =COUNTIFS('Léo'!$B$2:$B$500,$A15,'Léo'!$K$2:$K$500,"À tester") | G15: =COUNTIFS('Léo'!$B$2:$B$500,$A15,'Léo'!$K$2:$K$500,"Non applicable") | H15: =IF(B15-G15=0,0,C15/(B15-G15))
A16: Connecteurs | B16: =COUNTIF('Léo'!$B$2:$B$500,$A16) | C16: =COUNTIFS('Léo'!$B$2:$B$500,$A16,'Léo'!$K$2:$K$500,"OK") | D16: =COUNTIFS('Léo'!$B$2:$B$500,$A16,'Léo'!$K$2:$K$500,"KO") | E16: =COUNTIFS('Léo'!$B$2:$B$500,$A16,'Léo'!$K$2:$K$500,"Bloqué") | F16: =COUNTIFS('Léo'!$B$2:$B$500,$A16,'Léo'!$K$2:$K$500,"À tester") | G16: =COUNTIFS('Léo'!$B$2:$B$500,$A16,'Léo'!$K$2:$K$500,"Non applicable") | H16: =IF(B16-G16=0,0,C16/(B16-G16))
A17: Monde 3D | B17: =COUNTIF('Léo'!$B$2:$B$500,$A17) | C17: =COUNTIFS('Léo'!$B$2:$B$500,$A17,'Léo'!$K$2:$K$500,"OK") | D17: =COUNTIFS('Léo'!$B$2:$B$500,$A17,'Léo'!$K$2:$K$500,"KO") | E17: =COUNTIFS('Léo'!$B$2:$B$500,$A17,'Léo'!$K$2:$K$500,"Bloqué") | F17: =COUNTIFS('Léo'!$B$2:$B$500,$A17,'Léo'!$K$2:$K$500,"À tester") | G17: =COUNTIFS('Léo'!$B$2:$B$500,$A17,'Léo'!$K$2:$K$500,"Non applicable") | H17: =IF(B17-G17=0,0,C17/(B17-G17))
A18: Offre et contact | B18: =COUNTIF('Léo'!$B$2:$B$500,$A18) | C18: =COUNTIFS('Léo'!$B$2:$B$500,$A18,'Léo'!$K$2:$K$500,"OK") | D18: =COUNTIFS('Léo'!$B$2:$B$500,$A18,'Léo'!$K$2:$K$500,"KO") | E18: =COUNTIFS('Léo'!$B$2:$B$500,$A18,'Léo'!$K$2:$K$500,"Bloqué") | F18: =COUNTIFS('Léo'!$B$2:$B$500,$A18,'Léo'!$K$2:$K$500,"À tester") | G18: =COUNTIFS('Léo'!$B$2:$B$500,$A18,'Léo'!$K$2:$K$500,"Non applicable") | H18: =IF(B18-G18=0,0,C18/(B18-G18))
A19: Total | B19: =SUM(B6:B18) | C19: =SUM(C6:C18) | D19: =SUM(D6:D18) | E19: =SUM(E6:E18) | F19: =SUM(F6:F18) | G19: =SUM(G6:G18) | H19: =IF(B19-G19=0,0,C19/(B19-G19))
A21: Place de marché
A22: Module | B22: Cas | C22: OK | D22: KO | E22: Bloqué | F22: À tester | G22: Non applicable | H22: % passé
A23: Accueil et recherche | B23: =COUNTIF('Place de marché'!$B$2:$B$500,$A23) | C23: =COUNTIFS('Place de marché'!$B$2:$B$500,$A23,'Place de marché'!$K$2:$K$500,"OK") | D23: =COUNTIFS('Place de marché'!$B$2:$B$500,$A23,'Place de marché'!$K$2:$K$500,"KO") | E23: =COUNTIFS('Place de marché'!$B$2:$B$500,$A23,'Place de marché'!$K$2:$K$500,"Bloqué") | F23: =COUNTIFS('Place de marché'!$B$2:$B$500,$A23,'Place de marché'!$K$2:$K$500,"À tester") | G23: =COUNTIFS('Place de marché'!$B$2:$B$500,$A23,'Place de marché'!$K$2:$K$500,"Non applicable") | H23: =IF(B23-G23=0,0,C23/(B23-G23))
A24: Fiche article | B24: =COUNTIF('Place de marché'!$B$2:$B$500,$A24) | C24: =COUNTIFS('Place de marché'!$B$2:$B$500,$A24,'Place de marché'!$K$2:$K$500,"OK") | D24: =COUNTIFS('Place de marché'!$B$2:$B$500,$A24,'Place de marché'!$K$2:$K$500,"KO") | E24: =COUNTIFS('Place de marché'!$B$2:$B$500,$A24,'Place de marché'!$K$2:$K$500,"Bloqué") | F24: =COUNTIFS('Place de marché'!$B$2:$B$500,$A24,'Place de marché'!$K$2:$K$500,"À tester") | G24: =COUNTIFS('Place de marché'!$B$2:$B$500,$A24,'Place de marché'!$K$2:$K$500,"Non applicable") | H24: =IF(B24-G24=0,0,C24/(B24-G24))
A25: Panier et commande | B25: =COUNTIF('Place de marché'!$B$2:$B$500,$A25) | C25: =COUNTIFS('Place de marché'!$B$2:$B$500,$A25,'Place de marché'!$K$2:$K$500,"OK") | D25: =COUNTIFS('Place de marché'!$B$2:$B$500,$A25,'Place de marché'!$K$2:$K$500,"KO") | E25: =COUNTIFS('Place de marché'!$B$2:$B$500,$A25,'Place de marché'!$K$2:$K$500,"Bloqué") | F25: =COUNTIFS('Place de marché'!$B$2:$B$500,$A25,'Place de marché'!$K$2:$K$500,"À tester") | G25: =COUNTIFS('Place de marché'!$B$2:$B$500,$A25,'Place de marché'!$K$2:$K$500,"Non applicable") | H25: =IF(B25-G25=0,0,C25/(B25-G25))
A26: Compte | B26: =COUNTIF('Place de marché'!$B$2:$B$500,$A26) | C26: =COUNTIFS('Place de marché'!$B$2:$B$500,$A26,'Place de marché'!$K$2:$K$500,"OK") | D26: =COUNTIFS('Place de marché'!$B$2:$B$500,$A26,'Place de marché'!$K$2:$K$500,"KO") | E26: =COUNTIFS('Place de marché'!$B$2:$B$500,$A26,'Place de marché'!$K$2:$K$500,"Bloqué") | F26: =COUNTIFS('Place de marché'!$B$2:$B$500,$A26,'Place de marché'!$K$2:$K$500,"À tester") | G26: =COUNTIFS('Place de marché'!$B$2:$B$500,$A26,'Place de marché'!$K$2:$K$500,"Non applicable") | H26: =IF(B26-G26=0,0,C26/(B26-G26))
A27: Espace vendeuse | B27: =COUNTIF('Place de marché'!$B$2:$B$500,$A27) | C27: =COUNTIFS('Place de marché'!$B$2:$B$500,$A27,'Place de marché'!$K$2:$K$500,"OK") | D27: =COUNTIFS('Place de marché'!$B$2:$B$500,$A27,'Place de marché'!$K$2:$K$500,"KO") | E27: =COUNTIFS('Place de marché'!$B$2:$B$500,$A27,'Place de marché'!$K$2:$K$500,"Bloqué") | F27: =COUNTIFS('Place de marché'!$B$2:$B$500,$A27,'Place de marché'!$K$2:$K$500,"À tester") | G27: =COUNTIFS('Place de marché'!$B$2:$B$500,$A27,'Place de marché'!$K$2:$K$500,"Non applicable") | H27: =IF(B27-G27=0,0,C27/(B27-G27))
A28: Messagerie | B28: =COUNTIF('Place de marché'!$B$2:$B$500,$A28) | C28: =COUNTIFS('Place de marché'!$B$2:$B$500,$A28,'Place de marché'!$K$2:$K$500,"OK") | D28: =COUNTIFS('Place de marché'!$B$2:$B$500,$A28,'Place de marché'!$K$2:$K$500,"KO") | E28: =COUNTIFS('Place de marché'!$B$2:$B$500,$A28,'Place de marché'!$K$2:$K$500,"Bloqué") | F28: =COUNTIFS('Place de marché'!$B$2:$B$500,$A28,'Place de marché'!$K$2:$K$500,"À tester") | G28: =COUNTIFS('Place de marché'!$B$2:$B$500,$A28,'Place de marché'!$K$2:$K$500,"Non applicable") | H28: =IF(B28-G28=0,0,C28/(B28-G28))
A29: Services | B29: =COUNTIF('Place de marché'!$B$2:$B$500,$A29) | C29: =COUNTIFS('Place de marché'!$B$2:$B$500,$A29,'Place de marché'!$K$2:$K$500,"OK") | D29: =COUNTIFS('Place de marché'!$B$2:$B$500,$A29,'Place de marché'!$K$2:$K$500,"KO") | E29: =COUNTIFS('Place de marché'!$B$2:$B$500,$A29,'Place de marché'!$K$2:$K$500,"Bloqué") | F29: =COUNTIFS('Place de marché'!$B$2:$B$500,$A29,'Place de marché'!$K$2:$K$500,"À tester") | G29: =COUNTIFS('Place de marché'!$B$2:$B$500,$A29,'Place de marché'!$K$2:$K$500,"Non applicable") | H29: =IF(B29-G29=0,0,C29/(B29-G29))
A30: Général | B30: =COUNTIF('Place de marché'!$B$2:$B$500,$A30) | C30: =COUNTIFS('Place de marché'!$B$2:$B$500,$A30,'Place de marché'!$K$2:$K$500,"OK") | D30: =COUNTIFS('Place de marché'!$B$2:$B$500,$A30,'Place de marché'!$K$2:$K$500,"KO") | E30: =COUNTIFS('Place de marché'!$B$2:$B$500,$A30,'Place de marché'!$K$2:$K$500,"Bloqué") | F30: =COUNTIFS('Place de marché'!$B$2:$B$500,$A30,'Place de marché'!$K$2:$K$500,"À tester") | G30: =COUNTIFS('Place de marché'!$B$2:$B$500,$A30,'Place de marché'!$K$2:$K$500,"Non applicable") | H30: =IF(B30-G30=0,0,C30/(B30-G30))
A31: Total | B31: =SUM(B23:B30) | C31: =SUM(C23:C30) | D31: =SUM(D23:D30) | E31: =SUM(E23:E30) | F31: =SUM(F23:F30) | G31: =SUM(G23:G30) | H31: =IF(B31-G31=0,0,C31/(B31-G31))
A33: Anomalies ouvertes
A34: Bloquante | B34: =COUNTIFS(Anomalies!$E$2:$E$201,$A34,Anomalies!$L$2:$L$201,"<>Fermée",Anomalies!$L$2:$L$201,"<>Refusée")
A35: Majeure | B35: =COUNTIFS(Anomalies!$E$2:$E$201,$A35,Anomalies!$L$2:$L$201,"<>Fermée",Anomalies!$L$2:$L$201,"<>Refusée")
A36: Mineure | B36: =COUNTIFS(Anomalies!$E$2:$E$201,$A36,Anomalies!$L$2:$L$201,"<>Fermée",Anomalies!$L$2:$L$201,"<>Refusée")
A37: Cosmétique | B37: =COUNTIFS(Anomalies!$E$2:$E$201,$A37,Anomalies!$L$2:$L$201,"<>Fermée",Anomalies!$L$2:$L$201,"<>Refusée")
A39: « % passé » = cas OK ÷ cas applicables (hors « Non applicable »).

Sheet Listes
A1: Statut | B1: Priorité | C1: Appareil | D1: Gravité | E1: Statut anomalie
A2: À tester | B2: Haute | C2: Téléphone | D2: Bloquante | E2: Ouverte
A3: OK | B3: Moyenne | C3: Ordinateur | D3: Majeure | E3: En correction
A4: KO | B4: Basse | C4: Téléphone + Ordinateur | D4: Mineure | E4: Corrigée — à revérifier
A5: Bloqué | D5: Cosmétique | E5: Fermée
A6: Non applicable | E6: Refusée

Sheet Léo
A1: ID | B1: Module | C1: Fonctionnalité | D1: Objectif du test | E1: Préconditions | F1: Étapes | G1: Données de test | H1: Résultat attendu | I1: Priorité | J1: Appareil | K1: Statut | L1: Résultat obtenu | M1: Remarques | N1: Testeur | O1: Date du test | P1: N° anomalie
A2: LEO-001 | B2: Accès et compte | C2: Page de connexion | D2: Se connecter à Léo | E2: Compte de test existant | F2: 1. Ouvrir /legion 2. Saisir e-mail et mot de passe 3. Valider | G2: Compte de test fourni par Beau | H2: On arrive sur « Mes entreprises ». Le fond de ville animé s'affiche sans ralentir la page. | I2: Haute | J2: Téléphone + Ordinateur | K2: À tester
A3: LEO-002 | B3: Accès et compte | C3: Continuer avec Finjaro | D3: Entrer dans Léo avec un compte Finjaro déjà connecté | E3: Être connecté sur finjaro.net | F3: 1. Aller sur la place de marché, connecté 2. Ouvrir Léo 3. Cliquer « Continuer avec Finjaro » | G3: — | H3: Connexion sans ressaisir le mot de passe, même compte. | I3: Haute | J3: Téléphone + Ordinateur | K3: À tester
A4: LEO-003 | B4: Accès et compte | C4: Connexion depuis Finjaro Accounting | D4: Passer d'Accounting à Léo sans se reconnecter | E4: Être connecté sur Accounting | F4: 1. Dans Accounting, ouvrir le lien vers Léo 2. Observer l'arrivée | G4: — | H4: On arrive connecté dans Léo, sur le même compte. Un lien réutilisé une 2e fois est refusé. | I4: Moyenne | J4: Ordinateur | K4: À tester
A5: LEO-004 | B5: Accès et compte | C5: Déconnexion | D5: Se déconnecter proprement | E5: Être connecté | F5: 1. Ouvrir le menu du compte 2. Se déconnecter 3. Revenir sur /legion | G5: — | H5: Retour à la page de connexion ; aucune donnée de l'entreprise visible. | I5: Haute | J5: Téléphone + Ordinateur | K5: À tester
A6: LEO-005 | B6: Accès et compte | C6: Langue FR / EN | D6: Changer la langue de l'interface | E6: Être connecté | F6: 1. Basculer FR → EN 2. Parcourir 3 écrans 3. Revenir en FR | G6: — | H6: Tous les libellés changent ; aucun texte resté dans l'autre langue. | I6: Moyenne | J6: Téléphone + Ordinateur | K6: À tester
A7: LEO-006 | B7: Accès et compte | C7: Thème sombre / clair | D7: Changer la palette | E7: Être connecté | F7: 1. Passer en clair 2. Parcourir salon, tâches, fiche agent 3. Repasser en sombre | G7: — | H7: Textes lisibles partout, aucun bloc blanc sur blanc ou noir sur noir. | I7: Basse | J7: Téléphone + Ordinateur | K7: À tester
A8: LEO-007 | B8: Fonder une entreprise | C8: Fonder à partir d'un modèle | D8: Créer une entreprise depuis un modèle prêt | E8: Être connecté | F8: 1. « Fonder une entreprise » 2. Choisir un modèle (ex. cabinet d'avocats) 3. Répondre à « Qui es-tu ? » et « Ce que tu veux obtenir » 4. Valider | G8: Nom : Test Cabinet | H8: L'entreprise est créée avec ses services et ses agents ; on arrive dans les salons. | I8: Haute | J8: Téléphone + Ordinateur | K8: À tester
A9: LEO-008 | B9: Fonder une entreprise | C9: Fonder sans modèle | D9: Créer une entreprise vide et choisir ses rôles | E9: Être connecté | F9: 1. Fonder sans modèle 2. Cliquer sur des rôles proposés 3. Valider | G9: Nom : Test Libre | H9: Seuls les rôles cliqués deviennent des agents. | I9: Haute | J9: Téléphone + Ordinateur | K9: À tester
A10: LEO-009 | B10: Fonder une entreprise | C10: Agent d'aide à la fondation | D10: Se faire guider pendant la fondation | E10: Écran Fonder ouvert | F10: 1. Poser une question à l'agent d'aide 2. Suivre sa suggestion | G10: « Je vends des pagnes en ligne » | H10: Réponse en français, pertinente pour le métier, en moins de 15 s. | I10: Moyenne | J10: Téléphone + Ordinateur | K10: À tester
A11: LEO-010 | B11: Fonder une entreprise | C11: Catalogue de métiers | D11: Ajouter un agent depuis le catalogue | E11: Entreprise créée | F11: 1. Agents → « + Agent » 2. Chercher un métier 3. L'ajouter | G11: Recherche : « comptable » | H11: Le métier est trouvé ; l'agent apparaît dans l'équipe avec photo et poste. | I11: Haute | J11: Téléphone + Ordinateur | K11: À tester
A12: LEO-011 | B12: Fonder une entreprise | C12: Mes entreprises / tour de contrôle | D12: Voir et ouvrir ses entreprises | E12: 2 entreprises créées | F12: 1. Ouvrir « Mes entreprises » 2. Ouvrir l'une puis l'autre | G12: — | H12: Les deux s'affichent avec leurs chiffres ; on entre dans la bonne. | I12: Moyenne | J12: Téléphone + Ordinateur | K12: À tester
A13: LEO-012 | B13: Salons et messages | C13: Écrire dans un salon | D13: Envoyer un message et recevoir une réponse d'agent | E13: Entreprise avec agents allumés | F13: 1. Ouvrir le salon Direction 2. Écrire une question simple | G13: « Bonjour, où en est-on ? » | H13: Un agent répond en français, en quelques secondes ; « X écrit… » s'affiche pendant l'attente. | I13: Haute | J13: Téléphone + Ordinateur | K13: À tester
... A77: LEO-076 | B77: Offre et contact | C77: Hors ligne | D77: Utiliser Léo sans réseau | E77: Mode avion | F77: 1. Couper le réseau 2. Naviguer | G77: — | H77: Un message clair signale l'absence de réseau ; rien ne plante. | I77: Basse | J77: Téléphone | K77: À tester

Sheet Place de marché
A1: ID | B1: Module | C1: Fonctionnalité | D1: Objectif du test | E1: Préconditions | F1: Étapes | G1: Données de test | H1: Résultat attendu | I1: Priorité | J1: Appareil | K1: Statut | L1: Résultat obtenu | M1: Remarques | N1: Testeur | O1: Date du test | P1: N° anomalie
A2: MKT-001 | B2: Accueil et recherche | C2: Accueil | D2: Découvrir les articles | E2: — | F2: 1. Ouvrir finjaro.net (ou staging) | G2: — | H2: Accueil rapide, articles avec photo, prix et boutique. | I2: Haute | J2: Téléphone + Ordinateur | K2: À tester
A3: MKT-002 | B3: Accueil et recherche | C3: Recherche | D3: Trouver un article | E3: — | F3: 1. Chercher un mot | G3: « robe » | H3: Résultats pertinents ; « aucun résultat » si rien. | I3: Haute | J3: Téléphone + Ordinateur | K3: À tester
A4: MKT-003 | B4: Accueil et recherche | C4: Catégories | D4: Parcourir une catégorie | E4: — | F4: 1. Ouvrir une catégorie | G4: — | H4: Seuls les articles de la catégorie s'affichent. | I4: Moyenne | J4: Téléphone + Ordinateur | K4: À tester
A5: MKT-004 | B5: Accueil et recherche | C5: Prix dans la monnaie du visiteur | D5: Voir les prix dans sa monnaie | E5: Tester depuis 2 pays (ou réglage du pays) | F5: 1. Régler le pays sur Royaume-Uni 2. Puis Canada 3. Puis Cameroun | G5: — | H5: £ au Royaume-Uni, $ CA au Canada, FCFA au Cameroun ; jamais FCFA par défaut pour un pays inconnu. | I5: Haute | J5: Téléphone + Ordinateur | K5: À tester
A6: MKT-005 | B6: Accueil et recherche | C6: Langue FR / EN | D6: Changer la langue | E6: — | F6: 1. Basculer la langue | G6: — | H6: Tous les textes changent ; aucun texte ne réduit Finjaro à un seul pays. | I6: Moyenne | J6: Téléphone + Ordinateur | K6: À tester
A7: MKT-006 | B7: Fiche article | C7: Fiche article | D7: Voir un article en détail | E7: — | F7: 1. Ouvrir un article | G7: — | H7: Photos, prix, description, boutique, bouton panier. | I7: Haute | J7: Téléphone + Ordinateur | K7: À tester
A8: MKT-007 | B8: Fiche article | C8: Prix sur demande | D8: Commander un article sans prix affiché | E8: Un article « prix sur demande » | F8: 1. L'ajouter au panier | G8: — | H8: L'ajout est possible et le prix est demandé à la vendeuse. | I8: Haute | J8: Téléphone + Ordinateur | K8: À tester
A9: MKT-008 | B9: Fiche article | C9: Contacter la vendeuse | D9: Écrire ou appeler depuis la fiche | E9: — | F9: 1. WhatsApp 2. Appel 3. Message dans l'appli | G9: — | H9: Chaque bouton ouvre le bon canal. | I9: Haute | J9: Téléphone | K9: À tester
A10: MKT-009 | B10: Fiche article | C10: Fiche traduite | D10: Lire une fiche dans l'autre langue | E10: Article saisi en français | F10: 1. Passer en anglais | G10: — | H10: La description est traduite. | I10: Basse | J10: Téléphone + Ordinateur | K10: À tester
A11: MKT-010 | B11: Panier et commande | C11: Panier sans compte | D11: Remplir un panier sans être connecté | E11: Déconnecté | F11: 1. Ajouter 2 articles 2. Ouvrir le panier | G11: — | H11: Le panier garde les articles ; la connexion n'est demandée qu'à la commande. | I11: Haute | J11: Téléphone + Ordinateur | K11: À tester
A12: MKT-011 | B12: Panier et commande | C12: Passer commande | D12: Commander avec paiement à la livraison | E12: Compte de test acheteur | F12: 1. Valider le panier 2. Adresse + téléphone 3. Confirmer | G12: Adresse de test | H12: Commande créée (statut new) ; la vendeuse est prévenue. | I12: Haute | J12: Téléphone + Ordinateur | K12: À tester
A13: MKT-012 | B13: Panier et commande | C13: Suivi de commande | D13: Suivre sa commande | E13: Une commande passée | F13: 1. Ouvrir « Mes commandes » | G13: — | H13: Statut à jour ; historique lisible. | I13: Haute | J13: Téléphone + Ordinateur | K13: À tester
... A36: MKT-035 | B36: Général | C36: Applications Android / iOS | D36: Vérifier l'appli installée | E36: Appli installée | F36: 1. Ouvrir l'appli 2. Refaire le parcours commande | G36: — | H36: Même comportement que sur finjaro.net. | I36: Haute | J36: Téléphone | K36: À tester

Sheet Anomalies
A1: N° anomalie | B1: Date | C1: Cas de test (ID) | D1: Application | E1: Gravité | F1: Titre court | G1: Étapes pour reproduire | H1: Résultat attendu | I1: Résultat obtenu | J1: Capture / vidéo (lien) | K1: Appareil et navigateur | L1: Statut | M1: Corrigé par / le | N1: Remarques
A2: =IF(F2="","","ANO-"&TEXT(ROW()-1,"000"))
A3: =IF(F3="","","ANO-"&TEXT(ROW()-1,"000"))
A4: =IF(F4="","","ANO-"&TEXT(ROW()-1,"000"))
A5: =IF(F5="","","ANO-"&TEXT(ROW()-1,"000"))
A6: =IF(F6="","","ANO-"&TEXT(ROW()-1,"000"))
A7: =IF(F7="","","ANO-"&TEXT(ROW()-1,"000"))
A8: =IF(F8="","","ANO-"&TEXT(ROW()-1,"000"))
A9: =IF(F9="","","ANO-"&TEXT(ROW()-1,"000"))
A10: =IF(F10="","","ANO-"&TEXT(ROW()-1,"000"))
A11: =IF(F11="","","ANO-"&TEXT(ROW()-1,"000"))
A12: =IF(F12="","","ANO-"&TEXT(ROW()-1,"000"))
A13: =IF(F13="","","ANO-"&TEXT(ROW()-1,"000"))
... A201: =IF(F201="","","ANO-"&TEXT(ROW()-1,"000"))
