Workbook

Sheet Articles
A1: Référence | B1: Article | C1: Catégorie | D1: Prix d'achat | E1: Prix de vente | F1: Stock | G1: Stock de départ | H1: Seuil d'alerte | I1: Marge par pièce | J1: Valeur du stock | K1: À commander ? | M1: Ma monnaie
A2: EX-01 | B2: EXEMPLE — Savon (à effacer) | C2: Exemple | D2: 100 | E2: 150 | F2: =IF(B2="","",G2+SUMIFS('Entrées de stock'!$C:$C,'Entrées de stock'!$B:$B,B2)-SUMIFS('Ventes du jour'!$C:$C,'Ventes du jour'!$B:$B,B2)) -> 27 | G2: 20 | H2: 5 | I2: =IF(OR(B2="",E2=""),"",E2-D2) -> 50 | J2: =IF(B2="","",F2*D2) -> 2700 | K2: =IF(OR(B2="",H2=""),"",IF(F2<=H2,"À commander","OK")) -> OK
A3: EX-02 | B3: EXEMPLE — Filtre à huile (à effacer) | C3: Exemple | D3: 400 | E3: 600 | F3: =IF(B3="","",G3+SUMIFS('Entrées de stock'!$C:$C,'Entrées de stock'!$B:$B,B3)-SUMIFS('Ventes du jour'!$C:$C,'Ventes du jour'!$B:$B,B3)) -> 2 | G3: 3 | H3: 2 | I3: =IF(OR(B3="",E3=""),"",E3-D3) -> 200 | J3: =IF(B3="","",F3*D3) -> 800 | K3: =IF(OR(B3="",H3=""),"",IF(F3<=H3,"À commander","OK")) -> À commander | M3: Comment remplir
F4: =IF(B4="","",G4+SUMIFS('Entrées de stock'!$C:$C,'Entrées de stock'!$B:$B,B4)-SUMIFS('Ventes du jour'!$C:$C,'Ventes du jour'!$B:$B,B4)) | I4: =IF(OR(B4="",E4=""),"",E4-D4) | J4: =IF(B4="","",F4*D4) | K4: =IF(OR(B4="",H4=""),"",IF(F4<=H4,"À commander","OK")) | M4: 1. Écris ta monnaie dans la case jaune ci-dessus (FCFA, €, £, $ CA, ₦, …).
F5: =IF(B5="","",G5+SUMIFS('Entrées de stock'!$C:$C,'Entrées de stock'!$B:$B,B5)-SUMIFS('Ventes du jour'!$C:$C,'Ventes du jour'!$B:$B,B5)) | I5: =IF(OR(B5="",E5=""),"",E5-D5) | J5: =IF(B5="","",F5*D5) | K5: =IF(OR(B5="",H5=""),"",IF(F5<=H5,"À commander","OK")) | M5: 2. Une ligne par article. La référence est facultative (code-barres, code maison).
F6: =IF(B6="","",G6+SUMIFS('Entrées de stock'!$C:$C,'Entrées de stock'!$B:$B,B6)-SUMIFS('Ventes du jour'!$C:$C,'Ventes du jour'!$B:$B,B6)) | I6: =IF(OR(B6="",E6=""),"",E6-D6) | J6: =IF(B6="","",F6*D6) | K6: =IF(OR(B6="",H6=""),"",IF(F6<=H6,"À commander","OK")) | M6: 3. Stock de départ : ce que tu comptes aujourd'hui sur l'étagère.
F7: =IF(B7="","",G7+SUMIFS('Entrées de stock'!$C:$C,'Entrées de stock'!$B:$B,B7)-SUMIFS('Ventes du jour'!$C:$C,'Ventes du jour'!$B:$B,B7)) | I7: =IF(OR(B7="",E7=""),"",E7-D7) | J7: =IF(B7="","",F7*D7) | K7: =IF(OR(B7="",H7=""),"",IF(F7<=H7,"À commander","OK")) | M7: 4. Seuil d'alerte : à ce niveau ou en dessous, l'article passe « À commander ».
F8: =IF(B8="","",G8+SUMIFS('Entrées de stock'!$C:$C,'Entrées de stock'!$B:$B,B8)-SUMIFS('Ventes du jour'!$C:$C,'Ventes du jour'!$B:$B,B8)) | I8: =IF(OR(B8="",E8=""),"",E8-D8) | J8: =IF(B8="","",F8*D8) | K8: =IF(OR(B8="",H8=""),"",IF(F8<=H8,"À commander","OK")) | M8: 5. Les colonnes grises se calculent seules : n'y écris rien.
F9: =IF(B9="","",G9+SUMIFS('Entrées de stock'!$C:$C,'Entrées de stock'!$B:$B,B9)-SUMIFS('Ventes du jour'!$C:$C,'Ventes du jour'!$B:$B,B9)) | I9: =IF(OR(B9="",E9=""),"",E9-D9) | J9: =IF(B9="","",F9*D9) | K9: =IF(OR(B9="",H9=""),"",IF(F9<=H9,"À commander","OK")) | M9: 6. Efface les lignes EXEMPLE quand tu as compris.
F10: =IF(B10="","",G10+SUMIFS('Entrées de stock'!$C:$C,'Entrées de stock'!$B:$B,B10)-SUMIFS('Ventes du jour'!$C:$C,'Ventes du jour'!$B:$B,B10)) | I10: =IF(OR(B10="",E10=""),"",E10-D10) | J10: =IF(B10="","",F10*D10) | K10: =IF(OR(B10="",H10=""),"",IF(F10<=H10,"À commander","OK"))
F11: =IF(B11="","",G11+SUMIFS('Entrées de stock'!$C:$C,'Entrées de stock'!$B:$B,B11)-SUMIFS('Ventes du jour'!$C:$C,'Ventes du jour'!$B:$B,B11)) | I11: =IF(OR(B11="",E11=""),"",E11-D11) | J11: =IF(B11="","",F11*D11) | K11: =IF(OR(B11="",H11=""),"",IF(F11<=H11,"À commander","OK"))
F12: =IF(B12="","",G12+SUMIFS('Entrées de stock'!$C:$C,'Entrées de stock'!$B:$B,B12)-SUMIFS('Ventes du jour'!$C:$C,'Ventes du jour'!$B:$B,B12)) | I12: =IF(OR(B12="",E12=""),"",E12-D12) | J12: =IF(B12="","",F12*D12) | K12: =IF(OR(B12="",H12=""),"",IF(F12<=H12,"À commander","OK"))
F13: =IF(B13="","",G13+SUMIFS('Entrées de stock'!$C:$C,'Entrées de stock'!$B:$B,B13)-SUMIFS('Ventes du jour'!$C:$C,'Ventes du jour'!$B:$B,B13)) | I13: =IF(OR(B13="",E13=""),"",E13-D13) | J13: =IF(B13="","",F13*D13) | K13: =IF(OR(B13="",H13=""),"",IF(F13<=H13,"À commander","OK"))
F14: =IF(B14="","",G14+SUMIFS('Entrées de stock'!$C:$C,'Entrées de stock'!$B:$B,B14)-SUMIFS('Ventes du jour'!$C:$C,'Ventes du jour'!$B:$B,B14)) | I14: =IF(OR(B14="",E14=""),"",E14-D14) | J14: =IF(B14="","",F14*D14) | K14: =IF(OR(B14="",H14=""),"",IF(F14<=H14,"À commander","OK"))
F15: =IF(B15="","",G15+SUMIFS('Entrées de stock'!$C:$C,'Entrées de stock'!$B:$B,B15)-SUMIFS('Ventes du jour'!$C:$C,'Ventes du jour'!$B:$B,B15)) | I15: =IF(OR(B15="",E15=""),"",E15-D15) | J15: =IF(B15="","",F15*D15) | K15: =IF(OR(B15="",H15=""),"",IF(F15<=H15,"À commander","OK"))
F16: =IF(B16="","",G16+SUMIFS('Entrées de stock'!$C:$C,'Entrées de stock'!$B:$B,B16)-SUMIFS('Ventes du jour'!$C:$C,'Ventes du jour'!$B:$B,B16)) | I16: =IF(OR(B16="",E16=""),"",E16-D16) | J16: =IF(B16="","",F16*D16) | K16: =IF(OR(B16="",H16=""),"",IF(F16<=H16,"À commander","OK"))
F17: =IF(B17="","",G17+SUMIFS('Entrées de stock'!$C:$C,'Entrées de stock'!$B:$B,B17)-SUMIFS('Ventes du jour'!$C:$C,'Ventes du jour'!$B:$B,B17)) | I17: =IF(OR(B17="",E17=""),"",E17-D17) | J17: =IF(B17="","",F17*D17) | K17: =IF(OR(B17="",H17=""),"",IF(F17<=H17,"À commander","OK"))
F18: =IF(B18="","",G18+SUMIFS('Entrées de stock'!$C:$C,'Entrées de stock'!$B:$B,B18)-SUMIFS('Ventes du jour'!$C:$C,'Ventes du jour'!$B:$B,B18)) | I18: =IF(OR(B18="",E18=""),"",E18-D18) | J18: =IF(B18="","",F18*D18) | K18: =IF(OR(B18="",H18=""),"",IF(F18<=H18,"À commander","OK"))
F19: =IF(B19="","",G19+SUMIFS('Entrées de stock'!$C:$C,'Entrées de stock'!$B:$B,B19)-SUMIFS('Ventes du jour'!$C:$C,'Ventes du jour'!$B:$B,B19)) | I19: =IF(OR(B19="",E19=""),"",E19-D19) | J19: =IF(B19="","",F19*D19) | K19: =IF(OR(B19="",H19=""),"",IF(F19<=H19,"À commander","OK"))
F20: =IF(B20="","",G20+SUMIFS('Entrées de stock'!$C:$C,'Entrées de stock'!$B:$B,B20)-SUMIFS('Ventes du jour'!$C:$C,'Ventes du jour'!$B:$B,B20)) | I20: =IF(OR(B20="",E20=""),"",E20-D20) | J20: =IF(B20="","",F20*D20) | K20: =IF(OR(B20="",H20=""),"",IF(F20<=H20,"À commander","OK"))
F21: =IF(B21="","",G21+SUMIFS('Entrées de stock'!$C:$C,'Entrées de stock'!$B:$B,B21)-SUMIFS('Ventes du jour'!$C:$C,'Ventes du jour'!$B:$B,B21)) | I21: =IF(OR(B21="",E21=""),"",E21-D21) | J21: =IF(B21="","",F21*D21) | K21: =IF(OR(B21="",H21=""),"",IF(F21<=H21,"À commander","OK"))
... F301: =IF(B301="","",G301+SUMIFS('Entrées de stock'!$C:$C,'Entrées de stock'!$B:$B,B301)-SUMIFS('Ventes du jour'!$C:$C,'Ventes du jour'!$B:$B,B301)) | I301: =IF(OR(B301="",E301=""),"",E301-D301) | J301: =IF(B301="","",F301*D301) | K301: =IF(OR(B301="",H301=""),"",IF(F301<=H301,"À commander","OK"))

Sheet Entrées de stock
A1: Entrées de stock — tout ce qui arrive sur tes étagères
A2: Une ligne par livraison reçue. Choisis l'article dans la liste. Le prix d'achat se remplit tout seul : change-le si le fournisseur a changé son prix. « Payé ? » : Non tant que tu dois l'argent.
A3: Date | B3: Article | C3: Quantité reçue | D3: Prix d'achat unitaire | E3: Total | F3: Fournisseur | G3: Payé ? | H3: Note
A4: 46266 | B4: EXEMPLE — Savon (à effacer) | C4: 10 | D4: =IF(B4="","",IFERROR(INDEX(Articles!$D:$D,MATCH(B4,Articles!$B:$B,0)),"")) -> 100 | E4: =IF(OR(C4="",D4=""),"",C4*D4) -> 1000 | F4: EXEMPLE — fournisseur | G4: Oui | H4: EXEMPLE — à effacer
D5: =IF(B5="","",IFERROR(INDEX(Articles!$D:$D,MATCH(B5,Articles!$B:$B,0)),"")) | E5: =IF(OR(C5="",D5=""),"",C5*D5)
D6: =IF(B6="","",IFERROR(INDEX(Articles!$D:$D,MATCH(B6,Articles!$B:$B,0)),"")) | E6: =IF(OR(C6="",D6=""),"",C6*D6)
D7: =IF(B7="","",IFERROR(INDEX(Articles!$D:$D,MATCH(B7,Articles!$B:$B,0)),"")) | E7: =IF(OR(C7="",D7=""),"",C7*D7)
D8: =IF(B8="","",IFERROR(INDEX(Articles!$D:$D,MATCH(B8,Articles!$B:$B,0)),"")) | E8: =IF(OR(C8="",D8=""),"",C8*D8)
D9: =IF(B9="","",IFERROR(INDEX(Articles!$D:$D,MATCH(B9,Articles!$B:$B,0)),"")) | E9: =IF(OR(C9="",D9=""),"",C9*D9)
D10: =IF(B10="","",IFERROR(INDEX(Articles!$D:$D,MATCH(B10,Articles!$B:$B,0)),"")) | E10: =IF(OR(C10="",D10=""),"",C10*D10)
D11: =IF(B11="","",IFERROR(INDEX(Articles!$D:$D,MATCH(B11,Articles!$B:$B,0)),"")) | E11: =IF(OR(C11="",D11=""),"",C11*D11)
D12: =IF(B12="","",IFERROR(INDEX(Articles!$D:$D,MATCH(B12,Articles!$B:$B,0)),"")) | E12: =IF(OR(C12="",D12=""),"",C12*D12)
D13: =IF(B13="","",IFERROR(INDEX(Articles!$D:$D,MATCH(B13,Articles!$B:$B,0)),"")) | E13: =IF(OR(C13="",D13=""),"",C13*D13)
D14: =IF(B14="","",IFERROR(INDEX(Articles!$D:$D,MATCH(B14,Articles!$B:$B,0)),"")) | E14: =IF(OR(C14="",D14=""),"",C14*D14)
D15: =IF(B15="","",IFERROR(INDEX(Articles!$D:$D,MATCH(B15,Articles!$B:$B,0)),"")) | E15: =IF(OR(C15="",D15=""),"",C15*D15)
D16: =IF(B16="","",IFERROR(INDEX(Articles!$D:$D,MATCH(B16,Articles!$B:$B,0)),"")) | E16: =IF(OR(C16="",D16=""),"",C16*D16)
... D603: =IF(B603="","",IFERROR(INDEX(Articles!$D:$D,MATCH(B603,Articles!$B:$B,0)),"")) | E603: =IF(OR(C603="",D603=""),"",C603*D603)

Sheet Ventes du jour
A1: Ventes du jour — une ligne par vente, jour après jour
A2: Choisis l'article dans la liste. Le prix se remplit tout seul : change-le si tu as fait une remise. Si un client paie à crédit, écris son nom.
A3: Date | B3: Article | C3: Quantité | D3: Prix unitaire | E3: Total | F3: Paiement | G3: Client (si crédit) | H3: Coût | I3: Marge | J3: Note
A4: 46266 | B4: EXEMPLE — Savon (à effacer) | C4: 3 | D4: =IF(B4="","",IFERROR(INDEX(Articles!$E:$E,MATCH(B4,Articles!$B:$B,0)),"")) -> 150 | E4: =IF(OR(C4="",D4=""),"",C4*D4) -> 450 | F4: Espèces | H4: =IF(OR(B4="",C4=""),"",C4*IFERROR(INDEX(Articles!$D:$D,MATCH(B4,Articles!$B:$B,0)),0)) -> 300 | I4: =IF(OR(E4="",H4=""),"",E4-H4) -> 150 | J4: EXEMPLE — à effacer
A5: 46266 | B5: EXEMPLE — Filtre à huile (à effacer) | C5: 1 | D5: =IF(B5="","",IFERROR(INDEX(Articles!$E:$E,MATCH(B5,Articles!$B:$B,0)),"")) -> 600 | E5: =IF(OR(C5="",D5=""),"",C5*D5) -> 600 | F5: Mobile money | H5: =IF(OR(B5="",C5=""),"",C5*IFERROR(INDEX(Articles!$D:$D,MATCH(B5,Articles!$B:$B,0)),0)) -> 400 | I5: =IF(OR(E5="",H5=""),"",E5-H5) -> 200 | J5: EXEMPLE — à effacer
D6: =IF(B6="","",IFERROR(INDEX(Articles!$E:$E,MATCH(B6,Articles!$B:$B,0)),"")) | E6: =IF(OR(C6="",D6=""),"",C6*D6) | H6: =IF(OR(B6="",C6=""),"",C6*IFERROR(INDEX(Articles!$D:$D,MATCH(B6,Articles!$B:$B,0)),0)) | I6: =IF(OR(E6="",H6=""),"",E6-H6)
D7: =IF(B7="","",IFERROR(INDEX(Articles!$E:$E,MATCH(B7,Articles!$B:$B,0)),"")) | E7: =IF(OR(C7="",D7=""),"",C7*D7) | H7: =IF(OR(B7="",C7=""),"",C7*IFERROR(INDEX(Articles!$D:$D,MATCH(B7,Articles!$B:$B,0)),0)) | I7: =IF(OR(E7="",H7=""),"",E7-H7)
D8: =IF(B8="","",IFERROR(INDEX(Articles!$E:$E,MATCH(B8,Articles!$B:$B,0)),"")) | E8: =IF(OR(C8="",D8=""),"",C8*D8) | H8: =IF(OR(B8="",C8=""),"",C8*IFERROR(INDEX(Articles!$D:$D,MATCH(B8,Articles!$B:$B,0)),0)) | I8: =IF(OR(E8="",H8=""),"",E8-H8)
D9: =IF(B9="","",IFERROR(INDEX(Articles!$E:$E,MATCH(B9,Articles!$B:$B,0)),"")) | E9: =IF(OR(C9="",D9=""),"",C9*D9) | H9: =IF(OR(B9="",C9=""),"",C9*IFERROR(INDEX(Articles!$D:$D,MATCH(B9,Articles!$B:$B,0)),0)) | I9: =IF(OR(E9="",H9=""),"",E9-H9)
D10: =IF(B10="","",IFERROR(INDEX(Articles!$E:$E,MATCH(B10,Articles!$B:$B,0)),"")) | E10: =IF(OR(C10="",D10=""),"",C10*D10) | H10: =IF(OR(B10="",C10=""),"",C10*IFERROR(INDEX(Articles!$D:$D,MATCH(B10,Articles!$B:$B,0)),0)) | I10: =IF(OR(E10="",H10=""),"",E10-H10)
D11: =IF(B11="","",IFERROR(INDEX(Articles!$E:$E,MATCH(B11,Articles!$B:$B,0)),"")) | E11: =IF(OR(C11="",D11=""),"",C11*D11) | H11: =IF(OR(B11="",C11=""),"",C11*IFERROR(INDEX(Articles!$D:$D,MATCH(B11,Articles!$B:$B,0)),0)) | I11: =IF(OR(E11="",H11=""),"",E11-H11)
D12: =IF(B12="","",IFERROR(INDEX(Articles!$E:$E,MATCH(B12,Articles!$B:$B,0)),"")) | E12: =IF(OR(C12="",D12=""),"",C12*D12) | H12: =IF(OR(B12="",C12=""),"",C12*IFERROR(INDEX(Articles!$D:$D,MATCH(B12,Articles!$B:$B,0)),0)) | I12: =IF(OR(E12="",H12=""),"",E12-H12)
D13: =IF(B13="","",IFERROR(INDEX(Articles!$E:$E,MATCH(B13,Articles!$B:$B,0)),"")) | E13: =IF(OR(C13="",D13=""),"",C13*D13) | H13: =IF(OR(B13="",C13=""),"",C13*IFERROR(INDEX(Articles!$D:$D,MATCH(B13,Articles!$B:$B,0)),0)) | I13: =IF(OR(E13="",H13=""),"",E13-H13)
D14: =IF(B14="","",IFERROR(INDEX(Articles!$E:$E,MATCH(B14,Articles!$B:$B,0)),"")) | E14: =IF(OR(C14="",D14=""),"",C14*D14) | H14: =IF(OR(B14="",C14=""),"",C14*IFERROR(INDEX(Articles!$D:$D,MATCH(B14,Articles!$B:$B,0)),0)) | I14: =IF(OR(E14="",H14=""),"",E14-H14)
D15: =IF(B15="","",IFERROR(INDEX(Articles!$E:$E,MATCH(B15,Articles!$B:$B,0)),"")) | E15: =IF(OR(C15="",D15=""),"",C15*D15) | H15: =IF(OR(B15="",C15=""),"",C15*IFERROR(INDEX(Articles!$D:$D,MATCH(B15,Articles!$B:$B,0)),0)) | I15: =IF(OR(E15="",H15=""),"",E15-H15)
D16: =IF(B16="","",IFERROR(INDEX(Articles!$E:$E,MATCH(B16,Articles!$B:$B,0)),"")) | E16: =IF(OR(C16="",D16=""),"",C16*D16) | H16: =IF(OR(B16="",C16=""),"",C16*IFERROR(INDEX(Articles!$D:$D,MATCH(B16,Articles!$B:$B,0)),0)) | I16: =IF(OR(E16="",H16=""),"",E16-H16)
D17: =IF(B17="","",IFERROR(INDEX(Articles!$E:$E,MATCH(B17,Articles!$B:$B,0)),"")) | E17: =IF(OR(C17="",D17=""),"",C17*D17) | H17: =IF(OR(B17="",C17=""),"",C17*IFERROR(INDEX(Articles!$D:$D,MATCH(B17,Articles!$B:$B,0)),0)) | I17: =IF(OR(E17="",H17=""),"",E17-H17)
... D2003: =IF(B2003="","",IFERROR(INDEX(Articles!$E:$E,MATCH(B2003,Articles!$B:$B,0)),"")) | E2003: =IF(OR(C2003="",D2003=""),"",C2003*D2003) | H2003: =IF(OR(B2003="",C2003=""),"",C2003*IFERROR(INDEX(Articles!$D:$D,MATCH(B2003,Articles!$B:$B,0)),0)) | I2003: =IF(OR(E2003="",H2003=""),"",E2003-H2003)

Sheet Caisse du jour
A1: Caisse du jour — une ligne par jour
A2: Le matin : la date et le fond de caisse. Pendant la journée : ce qui entre ou sort de la caisse en dehors des ventes (une dépense, de l'argent pris pour la maison). Le soir : compte les billets et les pièces, écris « Caisse comptée ». L'écart doit être 0.
A3: Date | B3: Fond de caisse (matin) | C3: Ventes en espèces | D3: Autres entrées d'espèces | E3: Sorties d'espèces | F3: Caisse attendue | G3: Caisse comptée (soir) | H3: Écart | I3: Ventes en mobile money (à vérifier sur le téléphone) | J3: Explication
A4: 46266 | B4: 500 | C4: =IF(A4="","",SUMIFS('Ventes du jour'!$E:$E,'Ventes du jour'!$A:$A,A4,'Ventes du jour'!$F:$F,"Espèces")) -> 450 | D4: 0 | E4: 100 | F4: =IF(A4="","",N(B4)+N(C4)+N(D4)-N(E4)) -> 850 | G4: 800 | H4: =IF(OR(A4="",G4=""),"",G4-F4) -> -50 | I4: =IF(A4="","",SUMIFS('Ventes du jour'!$E:$E,'Ventes du jour'!$A:$A,A4,'Ventes du jour'!$F:$F,"Mobile money")) -> 600 | J4: EXEMPLE — monnaie mal rendue ? À effacer
C5: =IF(A5="","",SUMIFS('Ventes du jour'!$E:$E,'Ventes du jour'!$A:$A,A5,'Ventes du jour'!$F:$F,"Espèces")) | F5: =IF(A5="","",N(B5)+N(C5)+N(D5)-N(E5)) | H5: =IF(OR(A5="",G5=""),"",G5-F5) | I5: =IF(A5="","",SUMIFS('Ventes du jour'!$E:$E,'Ventes du jour'!$A:$A,A5,'Ventes du jour'!$F:$F,"Mobile money"))
C6: =IF(A6="","",SUMIFS('Ventes du jour'!$E:$E,'Ventes du jour'!$A:$A,A6,'Ventes du jour'!$F:$F,"Espèces")) | F6: =IF(A6="","",N(B6)+N(C6)+N(D6)-N(E6)) | H6: =IF(OR(A6="",G6=""),"",G6-F6) | I6: =IF(A6="","",SUMIFS('Ventes du jour'!$E:$E,'Ventes du jour'!$A:$A,A6,'Ventes du jour'!$F:$F,"Mobile money"))
C7: =IF(A7="","",SUMIFS('Ventes du jour'!$E:$E,'Ventes du jour'!$A:$A,A7,'Ventes du jour'!$F:$F,"Espèces")) | F7: =IF(A7="","",N(B7)+N(C7)+N(D7)-N(E7)) | H7: =IF(OR(A7="",G7=""),"",G7-F7) | I7: =IF(A7="","",SUMIFS('Ventes du jour'!$E:$E,'Ventes du jour'!$A:$A,A7,'Ventes du jour'!$F:$F,"Mobile money"))
C8: =IF(A8="","",SUMIFS('Ventes du jour'!$E:$E,'Ventes du jour'!$A:$A,A8,'Ventes du jour'!$F:$F,"Espèces")) | F8: =IF(A8="","",N(B8)+N(C8)+N(D8)-N(E8)) | H8: =IF(OR(A8="",G8=""),"",G8-F8) | I8: =IF(A8="","",SUMIFS('Ventes du jour'!$E:$E,'Ventes du jour'!$A:$A,A8,'Ventes du jour'!$F:$F,"Mobile money"))
C9: =IF(A9="","",SUMIFS('Ventes du jour'!$E:$E,'Ventes du jour'!$A:$A,A9,'Ventes du jour'!$F:$F,"Espèces")) | F9: =IF(A9="","",N(B9)+N(C9)+N(D9)-N(E9)) | H9: =IF(OR(A9="",G9=""),"",G9-F9) | I9: =IF(A9="","",SUMIFS('Ventes du jour'!$E:$E,'Ventes du jour'!$A:$A,A9,'Ventes du jour'!$F:$F,"Mobile money"))
C10: =IF(A10="","",SUMIFS('Ventes du jour'!$E:$E,'Ventes du jour'!$A:$A,A10,'Ventes du jour'!$F:$F,"Espèces")) | F10: =IF(A10="","",N(B10)+N(C10)+N(D10)-N(E10)) | H10: =IF(OR(A10="",G10=""),"",G10-F10) | I10: =IF(A10="","",SUMIFS('Ventes du jour'!$E:$E,'Ventes du jour'!$A:$A,A10,'Ventes du jour'!$F:$F,"Mobile money"))
C11: =IF(A11="","",SUMIFS('Ventes du jour'!$E:$E,'Ventes du jour'!$A:$A,A11,'Ventes du jour'!$F:$F,"Espèces")) | F11: =IF(A11="","",N(B11)+N(C11)+N(D11)-N(E11)) | H11: =IF(OR(A11="",G11=""),"",G11-F11) | I11: =IF(A11="","",SUMIFS('Ventes du jour'!$E:$E,'Ventes du jour'!$A:$A,A11,'Ventes du jour'!$F:$F,"Mobile money"))
C12: =IF(A12="","",SUMIFS('Ventes du jour'!$E:$E,'Ventes du jour'!$A:$A,A12,'Ventes du jour'!$F:$F,"Espèces")) | F12: =IF(A12="","",N(B12)+N(C12)+N(D12)-N(E12)) | H12: =IF(OR(A12="",G12=""),"",G12-F12) | I12: =IF(A12="","",SUMIFS('Ventes du jour'!$E:$E,'Ventes du jour'!$A:$A,A12,'Ventes du jour'!$F:$F,"Mobile money"))
C13: =IF(A13="","",SUMIFS('Ventes du jour'!$E:$E,'Ventes du jour'!$A:$A,A13,'Ventes du jour'!$F:$F,"Espèces")) | F13: =IF(A13="","",N(B13)+N(C13)+N(D13)-N(E13)) | H13: =IF(OR(A13="",G13=""),"",G13-F13) | I13: =IF(A13="","",SUMIFS('Ventes du jour'!$E:$E,'Ventes du jour'!$A:$A,A13,'Ventes du jour'!$F:$F,"Mobile money"))
C14: =IF(A14="","",SUMIFS('Ventes du jour'!$E:$E,'Ventes du jour'!$A:$A,A14,'Ventes du jour'!$F:$F,"Espèces")) | F14: =IF(A14="","",N(B14)+N(C14)+N(D14)-N(E14)) | H14: =IF(OR(A14="",G14=""),"",G14-F14) | I14: =IF(A14="","",SUMIFS('Ventes du jour'!$E:$E,'Ventes du jour'!$A:$A,A14,'Ventes du jour'!$F:$F,"Mobile money"))
C15: =IF(A15="","",SUMIFS('Ventes du jour'!$E:$E,'Ventes du jour'!$A:$A,A15,'Ventes du jour'!$F:$F,"Espèces")) | F15: =IF(A15="","",N(B15)+N(C15)+N(D15)-N(E15)) | H15: =IF(OR(A15="",G15=""),"",G15-F15) | I15: =IF(A15="","",SUMIFS('Ventes du jour'!$E:$E,'Ventes du jour'!$A:$A,A15,'Ventes du jour'!$F:$F,"Mobile money"))
C16: =IF(A16="","",SUMIFS('Ventes du jour'!$E:$E,'Ventes du jour'!$A:$A,A16,'Ventes du jour'!$F:$F,"Espèces")) | F16: =IF(A16="","",N(B16)+N(C16)+N(D16)-N(E16)) | H16: =IF(OR(A16="",G16=""),"",G16-F16) | I16: =IF(A16="","",SUMIFS('Ventes du jour'!$E:$E,'Ventes du jour'!$A:$A,A16,'Ventes du jour'!$F:$F,"Mobile money"))
... C403: =IF(A403="","",SUMIFS('Ventes du jour'!$E:$E,'Ventes du jour'!$A:$A,A403,'Ventes du jour'!$F:$F,"Espèces")) | F403: =IF(A403="","",N(B403)+N(C403)+N(D403)-N(E403)) | H403: =IF(OR(A403="",G403=""),"",G403-F403) | I403: =IF(A403="","",SUMIFS('Ventes du jour'!$E:$E,'Ventes du jour'!$A:$A,A403,'Ventes du jour'!$F:$F,"Mobile money"))

Sheet Récap
A1: Où j'en suis
A2: Montants en : | B2: =IF(Articles!$N$1="","(écris ta monnaie dans Articles, case « Ma monnaie »)",Articles!$N$1) -> (écris ta monnaie dans Articles, case « Ma monnaie »)
A4: Jour à regarder | C4: Laisse vide pour aujourd'hui, ou écris une date.
A5: Jour affiché | B5: =IF(B4="",TODAY(),B4)
A7: La journée
A8: Ventes du jour | B8: =SUMIFS('Ventes du jour'!$E:$E,'Ventes du jour'!$A:$A,$B$5)
A9: dont Espèces | B9: =SUMIFS('Ventes du jour'!$E:$E,'Ventes du jour'!$A:$A,$B$5,'Ventes du jour'!$F:$F,"Espèces")
A10: dont Mobile money | B10: =SUMIFS('Ventes du jour'!$E:$E,'Ventes du jour'!$A:$A,$B$5,'Ventes du jour'!$F:$F,"Mobile money")
A11: dont Carte | B11: =SUMIFS('Ventes du jour'!$E:$E,'Ventes du jour'!$A:$A,$B$5,'Ventes du jour'!$F:$F,"Carte")
A12: dont Crédit | B12: =SUMIFS('Ventes du jour'!$E:$E,'Ventes du jour'!$A:$A,$B$5,'Ventes du jour'!$F:$F,"Crédit")
A13: Marge du jour | B13: =SUMIFS('Ventes du jour'!$I:$I,'Ventes du jour'!$A:$A,$B$5)
A14: Écart de caisse du jour | B14: =IFERROR(INDEX('Caisse du jour'!$H:$H,MATCH($B$5,'Caisse du jour'!$A:$A,0)),"") | C14: vide = caisse pas encore comptée ce jour-là
A16: Le mois de ce jour
A17: Ventes du mois | B17: =SUMIFS('Ventes du jour'!$E:$E,'Ventes du jour'!$A:$A,">="&(EOMONTH($B$5,-1)+1),'Ventes du jour'!$A:$A,"<="&EOMONTH($B$5,0))
A18: Marge du mois | B18: =SUMIFS('Ventes du jour'!$I:$I,'Ventes du jour'!$A:$A,">="&(EOMONTH($B$5,-1)+1),'Ventes du jour'!$A:$A,"<="&EOMONTH($B$5,0))
A19: Achats de stock du mois | B19: =SUMIFS('Entrées de stock'!$E:$E,'Entrées de stock'!$A:$A,">="&(EOMONTH($B$5,-1)+1),'Entrées de stock'!$A:$A,"<="&EOMONTH($B$5,0))
A20: Écarts de caisse du mois (cumulés) | B20: =SUMIFS('Caisse du jour'!$H:$H,'Caisse du jour'!$A:$A,">="&(EOMONTH($B$5,-1)+1),'Caisse du jour'!$A:$A,"<="&EOMONTH($B$5,0))
A22: Le stock
A23: Valeur du stock (au prix d'achat) | B23: =SUM(Articles!$J$2:$J$301)
A24: Articles à commander | B24: =COUNTIF(Articles!$K$2:$K$301,"À commander")
A25: Ce que je dois encore aux fournisseurs | B25: =SUMIFS('Entrées de stock'!$E:$E,'Entrées de stock'!$G:$G,"Non")
A27: Quand ce classeur devient trop lourd (plusieurs caisses, reçus à envoyer, codes-barres) : Finjaro Accounting, accounting.finjaro.net — tes articles s'y importent depuis ce fichier.
